airflow/METRICS.md
airflow/__init__.py
airflow/__main__.py
airflow/alembic.ini
airflow/configuration.py
airflow/customized_form_field_behaviours.schema.json
airflow/exceptions.py
airflow/git_version
airflow/logging_config.py
airflow/plugins_manager.py
airflow/policies.py
airflow/provider.yaml.schema.json
airflow/provider_info.schema.json
airflow/providers_manager.py
airflow/py.typed
airflow/sentry.py
airflow/settings.py
airflow/stats.py
airflow/typing_compat.py
airflow/version.py
airflow/_shared/__init__.py
airflow/_shared/logging/__init__.py
airflow/_shared/logging/_config.py
airflow/_shared/logging/_noncaching.py
airflow/_shared/logging/percent_formatter.py
airflow/_shared/logging/structlog.py
airflow/_shared/logging/types.py
airflow/_shared/secrets_masker/__init__.py
airflow/_shared/secrets_masker/secrets_masker.py
airflow/_shared/timezones/__init__.py
airflow/_shared/timezones/timezone.py
airflow/_vendor/README.md
airflow/_vendor/__init__.py
airflow/_vendor/vendor.md
airflow/api/__init__.py
airflow/api/client/__init__.py
airflow/api/client/local_client.py
airflow/api/common/__init__.py
airflow/api/common/airflow_health.py
airflow/api/common/delete_dag.py
airflow/api/common/mark_tasks.py
airflow/api/common/trigger_dag.py
airflow/api_fastapi/__init__.py
airflow/api_fastapi/app.py
airflow/api_fastapi/main.py
airflow/api_fastapi/auth/__init__.py
airflow/api_fastapi/auth/tokens.py
airflow/api_fastapi/auth/managers/__init__.py
airflow/api_fastapi/auth/managers/base_auth_manager.py
airflow/api_fastapi/auth/managers/exceptions.py
airflow/api_fastapi/auth/managers/models/__init__.py
airflow/api_fastapi/auth/managers/models/base_user.py
airflow/api_fastapi/auth/managers/models/batch_apis.py
airflow/api_fastapi/auth/managers/models/resource_details.py
airflow/api_fastapi/auth/managers/simple/__init__.py
airflow/api_fastapi/auth/managers/simple/simple_auth_manager.py
airflow/api_fastapi/auth/managers/simple/user.py
airflow/api_fastapi/auth/managers/simple/utils.py
apache_airflow_core-3.1.7rc1.dist-info/METADATA
apache_airflow_core-3.1.7rc1.dist-info/WHEEL
apache_airflow_core-3.1.7rc1.dist-info/entry_points.txt
apache_airflow_core-3.1.7rc1.dist-info/licenses/LICENSE
apache_airflow_core-3.1.7rc1.dist-info/licenses/NOTICE
apache_airflow_core-3.1.7rc1.dist-info/RECORD
